astro_ghost/DLR.py
astro_ghost/MLP_lupton.hdf5
astro_ghost/NEDQueryFunctions.py
astro_ghost/PS1QueryFunctions.py
astro_ghost/SimbadQueryFunctions.py
astro_ghost/Star_Galaxy_RealisticModel_GHOST_PS1ClassLabels.sav
astro_ghost/TNSQueryFunctions.py
astro_ghost/__init__.py
astro_ghost/_version.py
astro_ghost/conftest.py
astro_ghost/ghostHelperFunctions.py
astro_ghost/gradientAscent.py
astro_ghost/gwgc_good.csv
astro_ghost/hostMatching.py
astro_ghost/photoz_helper.py
astro_ghost/sourceCleaning.py
astro_ghost/starSeparation.py
astro_ghost/stellarLocus.py
astro_ghost/tonry_ps1_locus.txt
tests/__init__.py
tests/debug.py
tests/test_tutorial.py
astro_ghost-2.2.3.dist-info/LICENSE.rst
astro_ghost-2.2.3.dist-info/METADATA
astro_ghost-2.2.3.dist-info/WHEEL
astro_ghost-2.2.3.dist-info/top_level.txt
astro_ghost-2.2.3.dist-info/RECORD
