Metadata-Version: 2.1
Name: astro-ghost
Version: 2.2.3
Summary: Database of supernovae and the photometric and spectroscopic properties of their host galaxies
Home-page: http://astro-ghost.readthedocs.io
Author: Alexander Gagliano
Author-email: gaglian2@illinois.edu
License: GNU GPL v3+
Classifier: Programming Language :: Python :: 3
Classifier: License :: OSI Approved :: MIT License
Classifier: Operating System :: OS Independent
Requires-Python: >=3.7
License-File: licenses/LICENSE.rst
Requires-Dist: astropy
Requires-Dist: pytest
Requires-Dist: pandas
Requires-Dist: scikit-learn<1.3.0
Requires-Dist: numpy<1.25.0,>=1.19.0
Requires-Dist: mastcasjobs
Requires-Dist: seaborn
Requires-Dist: matplotlib
Requires-Dist: joypy
Requires-Dist: photutils
Requires-Dist: scipy
Requires-Dist: datetime
Requires-Dist: requests
Requires-Dist: imblearn
Requires-Dist: rfpimp
Requires-Dist: Pillow
Requires-Dist: opencv-python
Requires-Dist: pyvo
Requires-Dist: astroquery
Requires-Dist: tensorflow
Requires-Dist: sfdmap2
Requires-Dist: importlib-resources
Provides-Extra: all
Provides-Extra: docs
Requires-Dist: sphinx; extra == "docs"
Requires-Dist: sphinx-automodapi; extra == "docs"
Requires-Dist: sphinx-astropy; extra == "docs"
Requires-Dist: sphinx-rtd-theme; extra == "docs"
Requires-Dist: sphinx-toolbox; extra == "docs"
Requires-Dist: sphinx-copybutton; extra == "docs"
Provides-Extra: test
Requires-Dist: pytest; extra == "test"
Requires-Dist: pytest-doctestplus; extra == "test"
Requires-Dist: pytest-cov; extra == "test"
Requires-Dist: pytest-astropy; extra == "test"
